{
  "distance": 7,
  "rounds": 7,
  "physical_error_rate": 0.00361064,
  "error_rate": 0.00361064,
  "shots": 100000,
  "seed": 79054558,
  "data_qubits": 49,
  "ancilla_qubits": 48,
  "active_qubits": 97,
  "stim_label_span": 118,
  "detectors": 336,
  "matching_edges": 1558,
  "logical_errors": 270,
  "logical_error_rate": 0.0027,
  "stim_version": "1.15.0",
  "pymatching_version": "2.4.0",
  "replica": 3,
  "elapsed_sec": 0.9917135238647461,
  "host": "ip-10-3-132-171.ec2.internal",
  "slurm_job_id": "104",
  "slurm_array_job_id": "24",
  "slurm_task_id": "79"
}