{
  "distance": 9,
  "rounds": 9,
  "physical_error_rate": 0.00553918,
  "error_rate": 0.00553918,
  "shots": 100000,
  "seed": 115054666,
  "data_qubits": 81,
  "ancilla_qubits": 80,
  "active_qubits": 161,
  "stim_label_span": 188,
  "detectors": 720,
  "matching_edges": 3534,
  "logical_errors": 1068,
  "logical_error_rate": 0.01068,
  "stim_version": "1.15.0",
  "pymatching_version": "2.4.0",
  "replica": 3,
  "elapsed_sec": 3.195521593093872,
  "host": "ip-10-3-128-213.ec2.internal",
  "slurm_job_id": "140",
  "slurm_array_job_id": "24",
  "slurm_task_id": "115"
}